cmsplugin_contact_form/__init__.py
cmsplugin_contact_form/apps.py
cmsplugin_contact_form/cms_plugins.py
cmsplugin_contact_form/models.py
cmsplugin_contact_form/templates/cmsplugin_contact_form/checkbox_field.html
cmsplugin_contact_form/templates/cmsplugin_contact_form/date_field.html
cmsplugin_contact_form/templates/cmsplugin_contact_form/datetime_field.html
cmsplugin_contact_form/templates/cmsplugin_contact_form/email_field.html
cmsplugin_contact_form/templates/cmsplugin_contact_form/form.html
cmsplugin_contact_form/templates/cmsplugin_contact_form/phone_field.html
cmsplugin_contact_form/templates/cmsplugin_contact_form/radio_field.html
cmsplugin_contact_form/templates/cmsplugin_contact_form/submit_field.html
cmsplugin_contact_form/templates/cmsplugin_contact_form/text_field.html
cmsplugin_contact_form/templates/cmsplugin_contact_form/textarea_field.html
cmsplugin_contact_form/templates/cmsplugin_contact_form/time_field.html
cmsplugin_contact_form-0.2.dist-info/LICENSE
cmsplugin_contact_form-0.2.dist-info/METADATA
cmsplugin_contact_form-0.2.dist-info/WHEEL
cmsplugin_contact_form-0.2.dist-info/top_level.txt
cmsplugin_contact_form-0.2.dist-info/RECORD
