Metadata-Version: 2.1
Name: cmsplugin-contact-form
Version: 0.2
Summary: A Django CMS plugin to create functional contact forms.
Home-page: https://github.com/juliarizza/djangocms_contact_form
Maintainer: Julia Rizza
Maintainer-email: contato@juliarizza.com
License: MIT
Keywords: django djangocms plugin form contact email
Platform: UNKNOWN
Classifier: Development Status :: 3 - Alpha
Classifier: Environment :: Web Environment
Classifier: Intended Audience :: Developers
Classifier: License :: OSI Approved :: MIT License
Classifier: Operating System :: OS Independent
Classifier: Programming Language :: Python :: 3
Classifier: Topic :: Internet :: WWW/HTTP
Classifier: Framework :: Django
Requires-Dist: setuptools
